{
  "nodes": [
    {
      "id": "meeting_detail_card",
      "label": "meeting-detail-card.tsx",
      "file_type": "code",
      "source_file": "src\\widgets\\meeting-detail\\ui\\meeting-detail-card\\meeting-detail-card.tsx",
      "source_location": "L1"
    },
    {
      "id": "meeting_detail_card_inforow",
      "label": "InfoRow()",
      "file_type": "code",
      "source_file": "src\\widgets\\meeting-detail\\ui\\meeting-detail-card\\meeting-detail-card.tsx",
      "source_location": "L31"
    },
    {
      "id": "meeting_detail_card_participantsrow",
      "label": "ParticipantsRow()",
      "file_type": "code",
      "source_file": "src\\widgets\\meeting-detail\\ui\\meeting-detail-card\\meeting-detail-card.tsx",
      "source_location": "L64"
    },
    {
      "id": "meeting_detail_card_hostrow",
      "label": "HostRow()",
      "file_type": "code",
      "source_file": "src\\widgets\\meeting-detail\\ui\\meeting-detail-card\\meeting-detail-card.tsx",
      "source_location": "L99"
    },
    {
      "id": "meeting_detail_card_infosection",
      "label": "InfoSection()",
      "file_type": "code",
      "source_file": "src\\widgets\\meeting-detail\\ui\\meeting-detail-card\\meeting-detail-card.tsx",
      "source_location": "L127"
    },
    {
      "id": "meeting_detail_card_actionrow",
      "label": "ActionRow()",
      "file_type": "code",
      "source_file": "src\\widgets\\meeting-detail\\ui\\meeting-detail-card\\meeting-detail-card.tsx",
      "source_location": "L162"
    }
  ],
  "edges": [
    {
      "source": "meeting_detail_card",
      "target": "lucide_react",
      "relation": "imports_from",
      "confidence": "EXTRACTED",
      "source_file": "src\\widgets\\meeting-detail\\ui\\meeting-detail-card\\meeting-detail-card.tsx",
      "source_location": "L3",
      "weight": 1.0
    },
    {
      "source": "meeting_detail_card",
      "target": "meeting",
      "relation": "imports_from",
      "confidence": "EXTRACTED",
      "source_file": "src\\widgets\\meeting-detail\\ui\\meeting-detail-card\\meeting-detail-card.tsx",
      "source_location": "L5",
      "weight": 1.0
    },
    {
      "source": "meeting_detail_card",
      "target": "meeting",
      "relation": "imports_from",
      "confidence": "EXTRACTED",
      "source_file": "src\\widgets\\meeting-detail\\ui\\meeting-detail-card\\meeting-detail-card.tsx",
      "source_location": "L6",
      "weight": 1.0
    },
    {
      "source": "meeting_detail_card",
      "target": "favorites",
      "relation": "imports_from",
      "confidence": "EXTRACTED",
      "source_file": "src\\widgets\\meeting-detail\\ui\\meeting-detail-card\\meeting-detail-card.tsx",
      "source_location": "L7",
      "weight": 1.0
    },
    {
      "source": "meeting_detail_card",
      "target": "utils",
      "relation": "imports_from",
      "confidence": "EXTRACTED",
      "source_file": "src\\widgets\\meeting-detail\\ui\\meeting-detail-card\\meeting-detail-card.tsx",
      "source_location": "L9",
      "weight": 1.0
    },
    {
      "source": "meeting_detail_card",
      "target": "avatar",
      "relation": "imports_from",
      "confidence": "EXTRACTED",
      "source_file": "src\\widgets\\meeting-detail\\ui\\meeting-detail-card\\meeting-detail-card.tsx",
      "source_location": "L10",
      "weight": 1.0
    },
    {
      "source": "meeting_detail_card",
      "target": "action_button",
      "relation": "imports_from",
      "confidence": "EXTRACTED",
      "source_file": "src\\widgets\\meeting-detail\\ui\\meeting-detail-card\\meeting-detail-card.tsx",
      "source_location": "L12",
      "weight": 1.0
    },
    {
      "source": "meeting_detail_card",
      "target": "ellipsis_menu",
      "relation": "imports_from",
      "confidence": "EXTRACTED",
      "source_file": "src\\widgets\\meeting-detail\\ui\\meeting-detail-card\\meeting-detail-card.tsx",
      "source_location": "L13",
      "weight": 1.0
    },
    {
      "source": "meeting_detail_card",
      "target": "meeting_detail_progress",
      "relation": "imports_from",
      "confidence": "EXTRACTED",
      "source_file": "src\\widgets\\meeting-detail\\ui\\meeting-detail-card\\meeting-detail-card.tsx",
      "source_location": "L14",
      "weight": 1.0
    },
    {
      "source": "meeting_detail_card",
      "target": "use_meeting_detail_card",
      "relation": "imports_from",
      "confidence": "EXTRACTED",
      "source_file": "src\\widgets\\meeting-detail\\ui\\meeting-detail-card\\meeting-detail-card.tsx",
      "source_location": "L15",
      "weight": 1.0
    },
    {
      "source": "meeting_detail_card",
      "target": "meeting_detail_card_constants",
      "relation": "imports_from",
      "confidence": "EXTRACTED",
      "source_file": "src\\widgets\\meeting-detail\\ui\\meeting-detail-card\\meeting-detail-card.tsx",
      "source_location": "L16",
      "weight": 1.0
    },
    {
      "source": "meeting_detail_card",
      "target": "meeting_detail_card_types",
      "relation": "imports_from",
      "confidence": "EXTRACTED",
      "source_file": "src\\widgets\\meeting-detail\\ui\\meeting-detail-card\\meeting-detail-card.tsx",
      "source_location": "L17",
      "weight": 1.0
    },
    {
      "source": "meeting_detail_card",
      "target": "meeting_detail_card_inforow",
      "relation": "contains",
      "confidence": "EXTRACTED",
      "source_file": "src\\widgets\\meeting-detail\\ui\\meeting-detail-card\\meeting-detail-card.tsx",
      "source_location": "L31",
      "weight": 1.0
    },
    {
      "source": "meeting_detail_card",
      "target": "meeting_detail_card_participantsrow",
      "relation": "contains",
      "confidence": "EXTRACTED",
      "source_file": "src\\widgets\\meeting-detail\\ui\\meeting-detail-card\\meeting-detail-card.tsx",
      "source_location": "L64",
      "weight": 1.0
    },
    {
      "source": "meeting_detail_card",
      "target": "meeting_detail_card_hostrow",
      "relation": "contains",
      "confidence": "EXTRACTED",
      "source_file": "src\\widgets\\meeting-detail\\ui\\meeting-detail-card\\meeting-detail-card.tsx",
      "source_location": "L99",
      "weight": 1.0
    },
    {
      "source": "meeting_detail_card",
      "target": "meeting_detail_card_infosection",
      "relation": "contains",
      "confidence": "EXTRACTED",
      "source_file": "src\\widgets\\meeting-detail\\ui\\meeting-detail-card\\meeting-detail-card.tsx",
      "source_location": "L127",
      "weight": 1.0
    },
    {
      "source": "meeting_detail_card",
      "target": "meeting_detail_card_actionrow",
      "relation": "contains",
      "confidence": "EXTRACTED",
      "source_file": "src\\widgets\\meeting-detail\\ui\\meeting-detail-card\\meeting-detail-card.tsx",
      "source_location": "L162",
      "weight": 1.0
    }
  ]
}
